easy_glue/__init__.py
easy_glue-0.0.1.dist-info/LICENSE
easy_glue-0.0.1.dist-info/METADATA
easy_glue-0.0.1.dist-info/WHEEL
easy_glue-0.0.1.dist-info/top_level.txt
easy_glue-0.0.1.dist-info/RECORD
