Metadata-Version: 2.1
Name: easy-glue
Version: 0.0.1
Summary: UNKNOWN
Home-page: https://github.com/da-huin/easy_glue
Author: JunYeong Park
Author-email: dahuin000@gmail.com
License: MIT
Download-URL: https://github.com/da-huin/easy_glue/archive/master.zip
Platform: UNKNOWN
Classifier: Programming Language :: Python :: 3
Requires-Dist: boto3
